CHANGELOG.md
LICENSE
MANIFEST.in
README.md
dev-requirements.txt
setup.cfg
setup.py
tox.ini
src/related/__init__.py
src/related/_init_fields.py
src/related/converters.py
src/related/decorators.py
src/related/dispatchers.py
src/related/fields.py
src/related/functions.py
src/related/types.py
src/related/validators.py
src/related_li.egg-info/PKG-INFO
src/related_li.egg-info/SOURCES.txt
src/related_li.egg-info/dependency_links.txt
src/related_li.egg-info/requires.txt
src/related_li.egg-info/top_level.txt
tests/test_types.py
tests/ex00_sets_hashes/__init__.py
tests/ex00_sets_hashes/models.py
tests/ex00_sets_hashes/test_sets_hashes.py
tests/ex01_compose_v2/__init__.py
tests/ex01_compose_v2/models.py
tests/ex01_compose_v2/test_compose_v2.py
tests/ex02_compose_v3_2/__init__.py
tests/ex02_compose_v3_2/models.py
tests/ex02_compose_v3_2/test_compose_v3_2.py
tests/ex03_company/__init__.py
tests/ex03_company/models.py
tests/ex03_company/test_company.py
tests/ex04_contact/__init__.py
tests/ex04_contact/models.py
tests/ex04_contact/test_contact.py
tests/ex05_field_names/test_renamed.py
tests/ex06_json/__init__.py
tests/ex06_json/models.py
tests/ex06_json/test_json.py
tests/ex07_serializer/__init__.py
tests/ex07_serializer/models.py
tests/ex07_serializer/test_serializer.py
tests/ex08_self_reference/__init__.py
tests/ex08_self_reference/models.py
tests/ex08_self_reference/test_self_reference.py
tests/issues/test_issue_0021.py
tests/issues/test_issue_009.py
tests/issues/test_issue_020.py