Metadata-Version: 1.1
Name: related-li
Version: 0.7.0
Summary: Related: Straightforward nested object models in Python
Home-page: UNKNOWN
Author: UNKNOWN
Author-email: UNKNOWN
License: MIT license
Keywords: related object models yaml json dict nested
Platform: UNKNOWN
Classifier: Development Status :: 2 - Pre-Alpha
Classifier: Intended Audience :: Developers
Classifier: License :: OSI Approved :: MIT License
Classifier: Natural Language :: English
Classifier: Programming Language :: Python :: 2
Classifier: Programming Language :: Python :: 2.7
Classifier: Programming Language :: Python :: 3
Classifier: Programming Language :: Python :: 3.4
Classifier: Programming Language :: Python :: 3.5
Classifier: Programming Language :: Python :: 3.6
Classifier: Programming Language :: Python :: 3.7
